{"units":[{"coName":"Origin","unitName":"Armored car","stats":{"vision":{"value":"10","hasValue":false},"movement":{"value":"20","hasValue":false},"movementType":{"value":"1","hasValue":false},"baseDefence":{"value":"30","hasValue":false},"armorType":{"value":0,"hasValue":false},"lAttack":{"value":0,"hasValue":false},"mAttack":{"value":0,"hasValue":false},"hAttack":{"value":0,"hasValue":false},"uAttack":{"value":0,"hasValue":false},"ammo":{"value":0,"hasValue":false},"attackInnerRad":{"value":0,"hasValue":false},"attackOuterRad":{"value":0,"hasValue":false},"price":{"value":0,"hasValue":false},"loadCapacity":{"value":0,"hasValue":false},"bounty":{"value":0,"hasValue":false},"isNeutralOnly":{"value":false,"hasValue":false},"canBeDetected":{"value":false,"hasValue":false},"canCapture":{"value":false,"hasValue":false},"canMoveAfterBuild":{"value":false,"hasValue":false},"canAttackAfterMove":{"value":false,"hasValue":false},"canCounterAttack":{"value":false,"hasValue":false}}},{"coName":"Origin","unitName":"Artillery","stats":{"vision":{"value":0,"hasValue":false},"movement":{"value":0,"hasValue":false},"movementType":{"value":0,"hasValue":false},"baseDefence":{"value":0,"hasValue":false},"armorType":{"value":0,"hasValue":false},"lAttack":{"value":0,"hasValue":false},"mAttack":{"value":0,"hasValue":false},"hAttack":{"value":0,"hasValue":false},"uAttack":{"value":0,"hasValue":false},"ammo":{"value":0,"hasValue":false},"attackInnerRad":{"value":0,"hasValue":false},"attackOuterRad":{"value":0,"hasValue":false},"price":{"value":0,"hasValue":false},"loadCapacity":{"value":0,"hasValue":false},"bounty":{"value":0,"hasValue":false},"isNeutralOnly":{"value":false,"hasValue":false},"canBeDetected":{"value":false,"hasValue":false},"canCapture":{"value":false,"hasValue":false},"canMoveAfterBuild":{"value":false,"hasValue":false},"canAttackAfterMove":{"value":false,"hasValue":false},"canCounterAttack":{"value":false,"hasValue":false}}},{"coName":"Origin","unitName":"Bazooka","stats":{"vision":{"value":0,"hasValue":false},"movement":{"value":0,"hasValue":false},"movementType":{"value":0,"hasValue":false},"baseDefence":{"value":0,"hasValue":false},"armorType":{"value":0,"hasValue":false},"lAttack":{"value":0,"hasValue":false},"mAttack":{"value":0,"hasValue":false},"hAttack":{"value":0,"hasValue":false},"uAttack":{"value":0,"hasValue":false},"ammo":{"value":0,"hasValue":false},"attackInnerRad":{"value":0,"hasValue":false},"attackOuterRad":{"value":0,"hasValue":false},"price":{"value":0,"hasValue":false},"loadCapacity":{"value":0,"hasValue":false},"bounty":{"value":0,"hasValue":false},"isNeutralOnly":{"value":false,"hasValue":false},"canBeDetected":{"value":false,"hasValue":false},"canCapture":{"value":false,"hasValue":false},"canMoveAfterBuild":{"value":false,"hasValue":false},"canAttackAfterMove":{"value":false,"hasValue":false},"canCounterAttack":{"value":false,"hasValue":false}}},{"coName":"Origin","unitName":"Cavalry","stats":{"vision":{"value":0,"hasValue":false},"movement":{"value":0,"hasValue":false},"movementType":{"value":0,"hasValue":false},"baseDefence":{"value":0,"hasValue":false},"armorType":{"value":0,"hasValue":false},"lAttack":{"value":0,"hasValue":false},"mAttack":{"value":0,"hasValue":false},"hAttack":{"value":0,"hasValue":false},"uAttack":{"value":0,"hasValue":false},"ammo":{"value":0,"hasValue":false},"attackInnerRad":{"value":0,"hasValue":false},"attackOuterRad":{"value":0,"hasValue":false},"price":{"value":0,"hasValue":false},"loadCapacity":{"value":0,"hasValue":false},"bounty":{"value":0,"hasValue":false},"isNeutralOnly":{"value":false,"hasValue":false},"canBeDetected":{"value":false,"hasValue":false},"canCapture":{"value":false,"hasValue":false},"canMoveAfterBuild":{"value":false,"hasValue":false},"canAttackAfterMove":{"value":false,"hasValue":false},"canCounterAttack":{"value":false,"hasValue":false}}},{"coName":"Origin","unitName":"Grenade Thrower","stats":{"vision":{"value":0,"hasValue":false},"movement":{"value":0,"hasValue":false},"movementType":{"value":0,"hasValue":false},"baseDefence":{"value":0,"hasValue":false},"armorType":{"value":0,"hasValue":false},"lAttack":{"value":0,"hasValue":false},"mAttack":{"value":0,"hasValue":false},"hAttack":{"value":0,"hasValue":false},"uAttack":{"value":0,"hasValue":false},"ammo":{"value":0,"hasValue":false},"attackInnerRad":{"value":0,"hasValue":false},"attackOuterRad":{"value":0,"hasValue":false},"price":{"value":0,"hasValue":false},"loadCapacity":{"value":0,"hasValue":false},"bounty":{"value":0,"hasValue":false},"isNeutralOnly":{"value":false,"hasValue":false},"canBeDetected":{"value":false,"hasValue":false},"canCapture":{"value":false,"hasValue":false},"canMoveAfterBuild":{"value":false,"hasValue":false},"canAttackAfterMove":{"value":false,"hasValue":false},"canCounterAttack":{"value":false,"hasValue":false}}},{"coName":"Origin","unitName":"Infantry","stats":{"vision":{"value":"1","hasValue":false},"movement":{"value":"2","hasValue":false},"movementType":{"value":0,"hasValue":false},"baseDefence":{"value":"3","hasValue":false},"armorType":{"value":0,"hasValue":false},"lAttack":{"value":"6","hasValue":false},"mAttack":{"value":"6","hasValue":false},"hAttack":{"value":"6","hasValue":false},"uAttack":{"value":0,"hasValue":false},"ammo":{"value":"2","hasValue":false},"attackInnerRad":{"value":"3","hasValue":false},"attackOuterRad":{"value":"3","hasValue":false},"price":{"value":0,"hasValue":false},"loadCapacity":{"value":0,"hasValue":false},"bounty":{"value":0,"hasValue":false},"isNeutralOnly":{"value":false,"hasValue":false},"canBeDetected":{"value":false,"hasValue":false},"canCapture":{"value":false,"hasValue":false},"canMoveAfterBuild":{"value":false,"hasValue":false},"canAttackAfterMove":{"value":false,"hasValue":false},"canCounterAttack":{"value":false,"hasValue":false}}},{"coName":"Origin","unitName":"Machine Gunner","stats":{"vision":{"value":0,"hasValue":false},"movement":{"value":0,"hasValue":false},"movementType":{"value":0,"hasValue":false},"baseDefence":{"value":0,"hasValue":false},"armorType":{"value":0,"hasValue":false},"lAttack":{"value":0,"hasValue":false},"mAttack":{"value":0,"hasValue":false},"hAttack":{"value":0,"hasValue":false},"uAttack":{"value":0,"hasValue":false},"ammo":{"value":0,"hasValue":false},"attackInnerRad":{"value":0,"hasValue":false},"attackOuterRad":{"value":0,"hasValue":false},"price":{"value":0,"hasValue":false},"loadCapacity":{"value":0,"hasValue":false},"bounty":{"value":0,"hasValue":false},"isNeutralOnly":{"value":false,"hasValue":false},"canBeDetected":{"value":false,"hasValue":false},"canCapture":{"value":false,"hasValue":false},"canMoveAfterBuild":{"value":false,"hasValue":false},"canAttackAfterMove":{"value":false,"hasValue":false},"canCounterAttack":{"value":false,"hasValue":false}}},{"coName":"Origin","unitName":"Tank","stats":{"vision":{"value":0,"hasValue":false},"movement":{"value":0,"hasValue":false},"movementType":{"value":0,"hasValue":false},"baseDefence":{"value":0,"hasValue":false},"armorType":{"value":0,"hasValue":false},"lAttack":{"value":0,"hasValue":false},"mAttack":{"value":0,"hasValue":false},"hAttack":{"value":0,"hasValue":false},"uAttack":{"value":0,"hasValue":false},"ammo":{"value":0,"hasValue":false},"attackInnerRad":{"value":0,"hasValue":false},"attackOuterRad":{"value":0,"hasValue":false},"price":{"value":0,"hasValue":false},"loadCapacity":{"value":0,"hasValue":false},"bounty":{"value":0,"hasValue":false},"isNeutralOnly":{"value":false,"hasValue":false},"canBeDetected":{"value":false,"hasValue":false},"canCapture":{"value":false,"hasValue":false},"canMoveAfterBuild":{"value":false,"hasValue":false},"canAttackAfterMove":{"value":false,"hasValue":false},"canCounterAttack":{"value":false,"hasValue":false}}},{"coName":"Origin","unitName":"Transport","stats":{"vision":{"value":0,"hasValue":false},"movement":{"value":0,"hasValue":false},"movementType":{"value":0,"hasValue":false},"baseDefence":{"value":0,"hasValue":false},"armorType":{"value":0,"hasValue":false},"lAttack":{"value":0,"hasValue":false},"mAttack":{"value":0,"hasValue":false},"hAttack":{"value":0,"hasValue":false},"uAttack":{"value":0,"hasValue":false},"ammo":{"value":0,"hasValue":false},"attackInnerRad":{"value":0,"hasValue":false},"attackOuterRad":{"value":0,"hasValue":false},"price":{"value":0,"hasValue":false},"loadCapacity":{"value":0,"hasValue":false},"bounty":{"value":0,"hasValue":false},"isNeutralOnly":{"value":false,"hasValue":false},"canBeDetected":{"value":false,"hasValue":false},"canCapture":{"value":false,"hasValue":false},"canMoveAfterBuild":{"value":false,"hasValue":false},"canAttackAfterMove":{"value":false,"hasValue":false},"canCounterAttack":{"value":false,"hasValue":false}}},{"coName":"Origin","unitName":"Bomber","stats":{"vision":{"value":0,"hasValue":false},"movement":{"value":0,"hasValue":false},"movementType":{"value":0,"hasValue":false},"baseDefence":{"value":0,"hasValue":false},"armorType":{"value":0,"hasValue":false},"lAttack":{"value":0,"hasValue":false},"mAttack":{"value":0,"hasValue":false},"hAttack":{"value":0,"hasValue":false},"uAttack":{"value":0,"hasValue":false},"ammo":{"value":0,"hasValue":false},"attackInnerRad":{"value":0,"hasValue":false},"attackOuterRad":{"value":0,"hasValue":false},"price":{"value":0,"hasValue":false},"loadCapacity":{"value":0,"hasValue":false},"bounty":{"value":0,"hasValue":false},"isNeutralOnly":{"value":false,"hasValue":false},"canBeDetected":{"value":false,"hasValue":false},"canCapture":{"value":false,"hasValue":false},"canMoveAfterBuild":{"value":false,"hasValue":false},"canAttackAfterMove":{"value":false,"hasValue":false},"canCounterAttack":{"value":false,"hasValue":false}}},{"coName":"Friedrich","unitName":"Armored car","stats":{"vision":{"value":0,"hasValue":false},"movement":{"value":0,"hasValue":false},"movementType":{"value":0,"hasValue":false},"baseDefence":{"value":0,"hasValue":false},"armorType":{"value":0,"hasValue":false},"lAttack":{"value":0,"hasValue":false},"mAttack":{"value":0,"hasValue":false},"hAttack":{"value":0,"hasValue":false},"uAttack":{"value":0,"hasValue":false},"ammo":{"value":0,"hasValue":false},"attackInnerRad":{"value":0,"hasValue":false},"attackOuterRad":{"value":0,"hasValue":false},"price":{"value":0,"hasValue":false},"loadCapacity":{"value":0,"hasValue":false},"bounty":{"value":0,"hasValue":false},"isNeutralOnly":{"value":false,"hasValue":false},"canBeDetected":{"value":false,"hasValue":false},"canCapture":{"value":false,"hasValue":false},"canMoveAfterBuild":{"value":false,"hasValue":false},"canAttackAfterMove":{"value":false,"hasValue":false},"canCounterAttack":{"value":false,"hasValue":false}}},{"coName":"Friedrich","unitName":"Artillery","stats":{"vision":{"value":0,"hasValue":false},"movement":{"value":0,"hasValue":false},"movementType":{"value":0,"hasValue":false},"baseDefence":{"value":0,"hasValue":false},"armorType":{"value":0,"hasValue":false},"lAttack":{"value":0,"hasValue":false},"mAttack":{"value":0,"hasValue":false},"hAttack":{"value":0,"hasValue":false},"uAttack":{"value":0,"hasValue":false},"ammo":{"value":0,"hasValue":false},"attackInnerRad":{"value":0,"hasValue":false},"attackOuterRad":{"value":0,"hasValue":false},"price":{"value":0,"hasValue":false},"loadCapacity":{"value":0,"hasValue":false},"bounty":{"value":0,"hasValue":false},"isNeutralOnly":{"value":false,"hasValue":false},"canBeDetected":{"value":false,"hasValue":false},"canCapture":{"value":false,"hasValue":false},"canMoveAfterBuild":{"value":false,"hasValue":false},"canAttackAfterMove":{"value":false,"hasValue":false},"canCounterAttack":{"value":false,"hasValue":false}}},{"coName":"Friedrich","unitName":"Bazooka","stats":{"vision":{"value":0,"hasValue":false},"movement":{"value":0,"hasValue":false},"movementType":{"value":0,"hasValue":false},"baseDefence":{"value":0,"hasValue":false},"armorType":{"value":0,"hasValue":false},"lAttack":{"value":0,"hasValue":false},"mAttack":{"value":0,"hasValue":false},"hAttack":{"value":0,"hasValue":false},"uAttack":{"value":0,"hasValue":false},"ammo":{"value":0,"hasValue":false},"attackInnerRad":{"value":0,"hasValue":false},"attackOuterRad":{"value":0,"hasValue":false},"price":{"value":0,"hasValue":false},"loadCapacity":{"value":0,"hasValue":false},"bounty":{"value":0,"hasValue":false},"isNeutralOnly":{"value":false,"hasValue":false},"canBeDetected":{"value":false,"hasValue":false},"canCapture":{"value":false,"hasValue":false},"canMoveAfterBuild":{"value":false,"hasValue":false},"canAttackAfterMove":{"value":false,"hasValue":false},"canCounterAttack":{"value":false,"hasValue":false}}},{"coName":"Friedrich","unitName":"Cavalry","stats":{"vision":{"value":0,"hasValue":false},"movement":{"value":0,"hasValue":false},"movementType":{"value":0,"hasValue":false},"baseDefence":{"value":0,"hasValue":false},"armorType":{"value":0,"hasValue":false},"lAttack":{"value":0,"hasValue":false},"mAttack":{"value":0,"hasValue":false},"hAttack":{"value":0,"hasValue":false},"uAttack":{"value":0,"hasValue":false},"ammo":{"value":0,"hasValue":false},"attackInnerRad":{"value":0,"hasValue":false},"attackOuterRad":{"value":0,"hasValue":false},"price":{"value":0,"hasValue":false},"loadCapacity":{"value":0,"hasValue":false},"bounty":{"value":0,"hasValue":false},"isNeutralOnly":{"value":false,"hasValue":false},"canBeDetected":{"value":false,"hasValue":false},"canCapture":{"value":false,"hasValue":false},"canMoveAfterBuild":{"value":false,"hasValue":false},"canAttackAfterMove":{"value":false,"hasValue":false},"canCounterAttack":{"value":false,"hasValue":false}}},{"coName":"Friedrich","unitName":"Grenade Thrower","stats":{"vision":{"value":0,"hasValue":false},"movement":{"value":0,"hasValue":false},"movementType":{"value":0,"hasValue":false},"baseDefence":{"value":0,"hasValue":false},"armorType":{"value":0,"hasValue":false},"lAttack":{"value":0,"hasValue":false},"mAttack":{"value":0,"hasValue":false},"hAttack":{"value":0,"hasValue":false},"uAttack":{"value":0,"hasValue":false},"ammo":{"value":0,"hasValue":false},"attackInnerRad":{"value":0,"hasValue":false},"attackOuterRad":{"value":0,"hasValue":false},"price":{"value":0,"hasValue":false},"loadCapacity":{"value":0,"hasValue":false},"bounty":{"value":0,"hasValue":false},"isNeutralOnly":{"value":false,"hasValue":false},"canBeDetected":{"value":false,"hasValue":false},"canCapture":{"value":false,"hasValue":false},"canMoveAfterBuild":{"value":false,"hasValue":false},"canAttackAfterMove":{"value":false,"hasValue":false},"canCounterAttack":{"value":false,"hasValue":false}}},{"coName":"Friedrich","unitName":"Infantry","stats":{"vision":{"value":0,"hasValue":false},"movement":{"value":0,"hasValue":false},"movementType":{"value":0,"hasValue":false},"baseDefence":{"value":0,"hasValue":false},"armorType":{"value":0,"hasValue":false},"lAttack":{"value":0,"hasValue":false},"mAttack":{"value":0,"hasValue":false},"hAttack":{"value":0,"hasValue":false},"uAttack":{"value":0,"hasValue":false},"ammo":{"value":0,"hasValue":false},"attackInnerRad":{"value":0,"hasValue":false},"attackOuterRad":{"value":0,"hasValue":false},"price":{"value":0,"hasValue":false},"loadCapacity":{"value":0,"hasValue":false},"bounty":{"value":0,"hasValue":false},"isNeutralOnly":{"value":false,"hasValue":false},"canBeDetected":{"value":false,"hasValue":false},"canCapture":{"value":false,"hasValue":false},"canMoveAfterBuild":{"value":false,"hasValue":false},"canAttackAfterMove":{"value":false,"hasValue":false},"canCounterAttack":{"value":false,"hasValue":false}}},{"coName":"Friedrich","unitName":"Machine Gunner","stats":{"vision":{"value":0,"hasValue":false},"movement":{"value":0,"hasValue":false},"movementType":{"value":0,"hasValue":false},"baseDefence":{"value":0,"hasValue":false},"armorType":{"value":0,"hasValue":false},"lAttack":{"value":0,"hasValue":false},"mAttack":{"value":0,"hasValue":false},"hAttack":{"value":0,"hasValue":false},"uAttack":{"value":0,"hasValue":false},"ammo":{"value":0,"hasValue":false},"attackInnerRad":{"value":0,"hasValue":false},"attackOuterRad":{"value":0,"hasValue":false},"price":{"value":0,"hasValue":false},"loadCapacity":{"value":0,"hasValue":false},"bounty":{"value":0,"hasValue":false},"isNeutralOnly":{"value":false,"hasValue":false},"canBeDetected":{"value":false,"hasValue":false},"canCapture":{"value":false,"hasValue":false},"canMoveAfterBuild":{"value":false,"hasValue":false},"canAttackAfterMove":{"value":false,"hasValue":false},"canCounterAttack":{"value":false,"hasValue":false}}},{"coName":"Friedrich","unitName":"Tank","stats":{"vision":{"value":0,"hasValue":false},"movement":{"value":0,"hasValue":false},"movementType":{"value":0,"hasValue":false},"baseDefence":{"value":0,"hasValue":false},"armorType":{"value":0,"hasValue":false},"lAttack":{"value":0,"hasValue":false},"mAttack":{"value":0,"hasValue":false},"hAttack":{"value":0,"hasValue":false},"uAttack":{"value":0,"hasValue":false},"ammo":{"value":0,"hasValue":false},"attackInnerRad":{"value":0,"hasValue":false},"attackOuterRad":{"value":0,"hasValue":false},"price":{"value":0,"hasValue":false},"loadCapacity":{"value":0,"hasValue":false},"bounty":{"value":0,"hasValue":false},"isNeutralOnly":{"value":false,"hasValue":false},"canBeDetected":{"value":false,"hasValue":false},"canCapture":{"value":false,"hasValue":false},"canMoveAfterBuild":{"value":false,"hasValue":false},"canAttackAfterMove":{"value":false,"hasValue":false},"canCounterAttack":{"value":false,"hasValue":false}}},{"coName":"Friedrich","unitName":"Transport","stats":{"vision":{"value":0,"hasValue":false},"movement":{"value":0,"hasValue":false},"movementType":{"value":0,"hasValue":false},"baseDefence":{"value":0,"hasValue":false},"armorType":{"value":0,"hasValue":false},"lAttack":{"value":0,"hasValue":false},"mAttack":{"value":0,"hasValue":false},"hAttack":{"value":0,"hasValue":false},"uAttack":{"value":0,"hasValue":false},"ammo":{"value":0,"hasValue":false},"attackInnerRad":{"value":0,"hasValue":false},"attackOuterRad":{"value":0,"hasValue":false},"price":{"value":0,"hasValue":false},"loadCapacity":{"value":0,"hasValue":false},"bounty":{"value":0,"hasValue":false},"isNeutralOnly":{"value":false,"hasValue":false},"canBeDetected":{"value":false,"hasValue":false},"canCapture":{"value":false,"hasValue":false},"canMoveAfterBuild":{"value":false,"hasValue":false},"canAttackAfterMove":{"value":false,"hasValue":false},"canCounterAttack":{"value":false,"hasValue":false}}},{"coName":"Friedrich","unitName":"Bomber","stats":{"vision":{"value":0,"hasValue":false},"movement":{"value":0,"hasValue":false},"movementType":{"value":0,"hasValue":false},"baseDefence":{"value":0,"hasValue":false},"armorType":{"value":0,"hasValue":false},"lAttack":{"value":0,"hasValue":false},"mAttack":{"value":0,"hasValue":false},"hAttack":{"value":0,"hasValue":false},"uAttack":{"value":0,"hasValue":false},"ammo":{"value":0,"hasValue":false},"attackInnerRad":{"value":0,"hasValue":false},"attackOuterRad":{"value":0,"hasValue":false},"price":{"value":0,"hasValue":false},"loadCapacity":{"value":0,"hasValue":false},"bounty":{"value":0,"hasValue":false},"isNeutralOnly":{"value":false,"hasValue":false},"canBeDetected":{"value":false,"hasValue":false},"canCapture":{"value":false,"hasValue":false},"canMoveAfterBuild":{"value":false,"hasValue":false},"canAttackAfterMove":{"value":false,"hasValue":false},"canCounterAttack":{"value":false,"hasValue":false}}},{"coName":"JulyWolf","unitName":"Armored car","stats":{"vision":{"value":0,"hasValue":false},"movement":{"value":0,"hasValue":false},"movementType":{"value":0,"hasValue":false},"baseDefence":{"value":0,"hasValue":false},"armorType":{"value":0,"hasValue":false},"lAttack":{"value":0,"hasValue":false},"mAttack":{"value":0,"hasValue":false},"hAttack":{"value":0,"hasValue":false},"uAttack":{"value":0,"hasValue":false},"ammo":{"value":0,"hasValue":false},"attackInnerRad":{"value":0,"hasValue":false},"attackOuterRad":{"value":0,"hasValue":false},"price":{"value":0,"hasValue":false},"loadCapacity":{"value":0,"hasValue":false},"bounty":{"value":0,"hasValue":false},"isNeutralOnly":{"value":false,"hasValue":false},"canBeDetected":{"value":false,"hasValue":false},"canCapture":{"value":false,"hasValue":false},"canMoveAfterBuild":{"value":false,"hasValue":false},"canAttackAfterMove":{"value":false,"hasValue":false},"canCounterAttack":{"value":false,"hasValue":false}}},{"coName":"JulyWolf","unitName":"Artillery","stats":{"vision":{"value":0,"hasValue":false},"movement":{"value":0,"hasValue":false},"movementType":{"value":0,"hasValue":false},"baseDefence":{"value":0,"hasValue":false},"armorType":{"value":0,"hasValue":false},"lAttack":{"value":0,"hasValue":false},"mAttack":{"value":0,"hasValue":false},"hAttack":{"value":0,"hasValue":false},"uAttack":{"value":0,"hasValue":false},"ammo":{"value":0,"hasValue":false},"attackInnerRad":{"value":0,"hasValue":false},"attackOuterRad":{"value":0,"hasValue":false},"price":{"value":0,"hasValue":false},"loadCapacity":{"value":0,"hasValue":false},"bounty":{"value":0,"hasValue":false},"isNeutralOnly":{"value":false,"hasValue":false},"canBeDetected":{"value":false,"hasValue":false},"canCapture":{"value":false,"hasValue":false},"canMoveAfterBuild":{"value":false,"hasValue":false},"canAttackAfterMove":{"value":false,"hasValue":false},"canCounterAttack":{"value":false,"hasValue":false}}},{"coName":"JulyWolf","unitName":"Bazooka","stats":{"vision":{"value":0,"hasValue":false},"movement":{"value":0,"hasValue":false},"movementType":{"value":0,"hasValue":false},"baseDefence":{"value":0,"hasValue":false},"armorType":{"value":0,"hasValue":false},"lAttack":{"value":0,"hasValue":false},"mAttack":{"value":0,"hasValue":false},"hAttack":{"value":0,"hasValue":false},"uAttack":{"value":0,"hasValue":false},"ammo":{"value":0,"hasValue":false},"attackInnerRad":{"value":0,"hasValue":false},"attackOuterRad":{"value":0,"hasValue":false},"price":{"value":0,"hasValue":false},"loadCapacity":{"value":0,"hasValue":false},"bounty":{"value":0,"hasValue":false},"isNeutralOnly":{"value":false,"hasValue":false},"canBeDetected":{"value":false,"hasValue":false},"canCapture":{"value":false,"hasValue":false},"canMoveAfterBuild":{"value":false,"hasValue":false},"canAttackAfterMove":{"value":false,"hasValue":false},"canCounterAttack":{"value":false,"hasValue":false}}},{"coName":"JulyWolf","unitName":"Cavalry","stats":{"vision":{"value":0,"hasValue":false},"movement":{"value":0,"hasValue":false},"movementType":{"value":0,"hasValue":false},"baseDefence":{"value":0,"hasValue":false},"armorType":{"value":0,"hasValue":false},"lAttack":{"value":0,"hasValue":false},"mAttack":{"value":0,"hasValue":false},"hAttack":{"value":0,"hasValue":false},"uAttack":{"value":0,"hasValue":false},"ammo":{"value":0,"hasValue":false},"attackInnerRad":{"value":0,"hasValue":false},"attackOuterRad":{"value":0,"hasValue":false},"price":{"value":0,"hasValue":false},"loadCapacity":{"value":0,"hasValue":false},"bounty":{"value":0,"hasValue":false},"isNeutralOnly":{"value":false,"hasValue":false},"canBeDetected":{"value":false,"hasValue":false},"canCapture":{"value":false,"hasValue":false},"canMoveAfterBuild":{"value":false,"hasValue":false},"canAttackAfterMove":{"value":false,"hasValue":false},"canCounterAttack":{"value":false,"hasValue":false}}},{"coName":"JulyWolf","unitName":"Grenade Thrower","stats":{"vision":{"value":0,"hasValue":false},"movement":{"value":0,"hasValue":false},"movementType":{"value":0,"hasValue":false},"baseDefence":{"value":0,"hasValue":false},"armorType":{"value":0,"hasValue":false},"lAttack":{"value":0,"hasValue":false},"mAttack":{"value":0,"hasValue":false},"hAttack":{"value":0,"hasValue":false},"uAttack":{"value":0,"hasValue":false},"ammo":{"value":0,"hasValue":false},"attackInnerRad":{"value":0,"hasValue":false},"attackOuterRad":{"value":0,"hasValue":false},"price":{"value":0,"hasValue":false},"loadCapacity":{"value":0,"hasValue":false},"bounty":{"value":0,"hasValue":false},"isNeutralOnly":{"value":false,"hasValue":false},"canBeDetected":{"value":false,"hasValue":false},"canCapture":{"value":false,"hasValue":false},"canMoveAfterBuild":{"value":false,"hasValue":false},"canAttackAfterMove":{"value":false,"hasValue":false},"canCounterAttack":{"value":false,"hasValue":false}}},{"coName":"JulyWolf","unitName":"Infantry","stats":{"vision":{"value":0,"hasValue":false},"movement":{"value":0,"hasValue":false},"movementType":{"value":0,"hasValue":false},"baseDefence":{"value":0,"hasValue":false},"armorType":{"value":0,"hasValue":false},"lAttack":{"value":0,"hasValue":false},"mAttack":{"value":0,"hasValue":false},"hAttack":{"value":0,"hasValue":false},"uAttack":{"value":0,"hasValue":false},"ammo":{"value":0,"hasValue":false},"attackInnerRad":{"value":0,"hasValue":false},"attackOuterRad":{"value":0,"hasValue":false},"price":{"value":0,"hasValue":false},"loadCapacity":{"value":0,"hasValue":false},"bounty":{"value":0,"hasValue":false},"isNeutralOnly":{"value":false,"hasValue":false},"canBeDetected":{"value":false,"hasValue":false},"canCapture":{"value":false,"hasValue":false},"canMoveAfterBuild":{"value":false,"hasValue":false},"canAttackAfterMove":{"value":false,"hasValue":false},"canCounterAttack":{"value":false,"hasValue":false}}},{"coName":"JulyWolf","unitName":"Machine Gunner","stats":{"vision":{"value":0,"hasValue":false},"movement":{"value":0,"hasValue":false},"movementType":{"value":0,"hasValue":false},"baseDefence":{"value":0,"hasValue":false},"armorType":{"value":0,"hasValue":false},"lAttack":{"value":0,"hasValue":false},"mAttack":{"value":0,"hasValue":false},"hAttack":{"value":0,"hasValue":false},"uAttack":{"value":0,"hasValue":false},"ammo":{"value":0,"hasValue":false},"attackInnerRad":{"value":0,"hasValue":false},"attackOuterRad":{"value":0,"hasValue":false},"price":{"value":0,"hasValue":false},"loadCapacity":{"value":0,"hasValue":false},"bounty":{"value":0,"hasValue":false},"isNeutralOnly":{"value":false,"hasValue":false},"canBeDetected":{"value":false,"hasValue":false},"canCapture":{"value":false,"hasValue":false},"canMoveAfterBuild":{"value":false,"hasValue":false},"canAttackAfterMove":{"value":false,"hasValue":false},"canCounterAttack":{"value":false,"hasValue":false}}},{"coName":"JulyWolf","unitName":"Tank","stats":{"vision":{"value":0,"hasValue":false},"movement":{"value":0,"hasValue":false},"movementType":{"value":0,"hasValue":false},"baseDefence":{"value":0,"hasValue":false},"armorType":{"value":0,"hasValue":false},"lAttack":{"value":0,"hasValue":false},"mAttack":{"value":0,"hasValue":false},"hAttack":{"value":0,"hasValue":false},"uAttack":{"value":0,"hasValue":false},"ammo":{"value":0,"hasValue":false},"attackInnerRad":{"value":0,"hasValue":false},"attackOuterRad":{"value":0,"hasValue":false},"price":{"value":0,"hasValue":false},"loadCapacity":{"value":0,"hasValue":false},"bounty":{"value":0,"hasValue":false},"isNeutralOnly":{"value":false,"hasValue":false},"canBeDetected":{"value":false,"hasValue":false},"canCapture":{"value":false,"hasValue":false},"canMoveAfterBuild":{"value":false,"hasValue":false},"canAttackAfterMove":{"value":false,"hasValue":false},"canCounterAttack":{"value":false,"hasValue":false}}},{"coName":"JulyWolf","unitName":"Transport","stats":{"vision":{"value":0,"hasValue":false},"movement":{"value":0,"hasValue":false},"movementType":{"value":0,"hasValue":false},"baseDefence":{"value":0,"hasValue":false},"armorType":{"value":0,"hasValue":false},"lAttack":{"value":0,"hasValue":false},"mAttack":{"value":0,"hasValue":false},"hAttack":{"value":0,"hasValue":false},"uAttack":{"value":0,"hasValue":false},"ammo":{"value":0,"hasValue":false},"attackInnerRad":{"value":0,"hasValue":false},"attackOuterRad":{"value":0,"hasValue":false},"price":{"value":0,"hasValue":false},"loadCapacity":{"value":0,"hasValue":false},"bounty":{"value":0,"hasValue":false},"isNeutralOnly":{"value":false,"hasValue":false},"canBeDetected":{"value":false,"hasValue":false},"canCapture":{"value":false,"hasValue":false},"canMoveAfterBuild":{"value":false,"hasValue":false},"canAttackAfterMove":{"value":false,"hasValue":false},"canCounterAttack":{"value":false,"hasValue":false}}},{"coName":"JulyWolf","unitName":"Bomber","stats":{"vision":{"value":0,"hasValue":false},"movement":{"value":0,"hasValue":false},"movementType":{"value":0,"hasValue":false},"baseDefence":{"value":0,"hasValue":false},"armorType":{"value":0,"hasValue":false},"lAttack":{"value":0,"hasValue":false},"mAttack":{"value":0,"hasValue":false},"hAttack":{"value":0,"hasValue":false},"uAttack":{"value":0,"hasValue":false},"ammo":{"value":0,"hasValue":false},"attackInnerRad":{"value":0,"hasValue":false},"attackOuterRad":{"value":0,"hasValue":false},"price":{"value":0,"hasValue":false},"loadCapacity":{"value":0,"hasValue":false},"bounty":{"value":0,"hasValue":false},"isNeutralOnly":{"value":false,"hasValue":false},"canBeDetected":{"value":false,"hasValue":false},"canCapture":{"value":false,"hasValue":false},"canMoveAfterBuild":{"value":false,"hasValue":false},"canAttackAfterMove":{"value":false,"hasValue":false},"canCounterAttack":{"value":false,"hasValue":false}}}],"upgrades":[{"fractionName":"League","unitName":"Armored car","upgradeList":[]},{"fractionName":"League","unitName":"Artillery","upgradeList":[]},{"fractionName":"League","unitName":"Bazooka","upgradeList":[]},{"fractionName":"League","unitName":"Cavalry","upgradeList":[]},{"fractionName":"League","unitName":"Grenade Thrower","upgradeList":[]},{"fractionName":"League","unitName":"Infantry","upgradeList":[{"rowNumber":0,"itemID":0,"itemName":"item","icon":0,"unitProperties":{"vision":{"value":0,"hasValue":false},"movement":{"value":0,"hasValue":false},"movementType":{"value":0,"hasValue":false},"baseDefence":{"value":0,"hasValue":false},"armorType":{"value":0,"hasValue":false},"lAttack":{"value":0,"hasValue":false},"mAttack":{"value":0,"hasValue":false},"hAttack":{"value":0,"hasValue":false},"uAttack":{"value":0,"hasValue":false},"ammo":{"value":0,"hasValue":false},"attackInnerRad":{"value":0,"hasValue":false},"attackOuterRad":{"value":0,"hasValue":false},"price":{"value":0,"hasValue":false},"loadCapacity":{"value":0,"hasValue":false},"bounty":{"value":0,"hasValue":false},"isNeutralOnly":{"value":false,"hasValue":false},"canBeDetected":{"value":false,"hasValue":false},"canCapture":{"value":false,"hasValue":false},"canMoveAfterBuild":{"value":false,"hasValue":false},"canAttackAfterMove":{"value":false,"hasValue":false},"canCounterAttack":{"value":false,"hasValue":false}},"price":"1"},{"rowNumber":1,"itemID":1,"itemName":"item","icon":"1","unitProperties":{"vision":{"value":0,"hasValue":false},"movement":{"value":0,"hasValue":false},"movementType":{"value":0,"hasValue":false},"baseDefence":{"value":0,"hasValue":false},"armorType":{"value":0,"hasValue":false},"lAttack":{"value":0,"hasValue":false},"mAttack":{"value":0,"hasValue":false},"hAttack":{"value":0,"hasValue":false},"uAttack":{"value":0,"hasValue":false},"ammo":{"value":0,"hasValue":false},"attackInnerRad":{"value":0,"hasValue":false},"attackOuterRad":{"value":0,"hasValue":false},"price":{"value":0,"hasValue":false},"loadCapacity":{"value":0,"hasValue":false},"bounty":{"value":0,"hasValue":false},"isNeutralOnly":{"value":false,"hasValue":false},"canBeDetected":{"value":false,"hasValue":false},"canCapture":{"value":false,"hasValue":false},"canMoveAfterBuild":{"value":false,"hasValue":false},"canAttackAfterMove":{"value":false,"hasValue":false},"canCounterAttack":{"value":false,"hasValue":false}},"price":"1"},{"rowNumber":2,"itemID":2,"itemName":"item","icon":"1","unitProperties":{"vision":{"value":0,"hasValue":false},"movement":{"value":0,"hasValue":false},"movementType":{"value":0,"hasValue":false},"baseDefence":{"value":0,"hasValue":false},"armorType":{"value":0,"hasValue":false},"lAttack":{"value":0,"hasValue":false},"mAttack":{"value":0,"hasValue":false},"hAttack":{"value":0,"hasValue":false},"uAttack":{"value":0,"hasValue":false},"ammo":{"value":0,"hasValue":false},"attackInnerRad":{"value":0,"hasValue":false},"attackOuterRad":{"value":0,"hasValue":false},"price":{"value":0,"hasValue":false},"loadCapacity":{"value":0,"hasValue":false},"bounty":{"value":0,"hasValue":false},"isNeutralOnly":{"value":false,"hasValue":false},"canBeDetected":{"value":false,"hasValue":false},"canCapture":{"value":false,"hasValue":false},"canMoveAfterBuild":{"value":false,"hasValue":false},"canAttackAfterMove":{"value":false,"hasValue":false},"canCounterAttack":{"value":false,"hasValue":false}},"price":"2"},{"rowNumber":3,"itemID":3,"itemName":"item","icon":"1","unitProperties":{"vision":{"value":0,"hasValue":false},"movement":{"value":0,"hasValue":false},"movementType":{"value":0,"hasValue":false},"baseDefence":{"value":0,"hasValue":false},"armorType":{"value":0,"hasValue":false},"lAttack":{"value":0,"hasValue":false},"mAttack":{"value":0,"hasValue":false},"hAttack":{"value":0,"hasValue":false},"uAttack":{"value":0,"hasValue":false},"ammo":{"value":0,"hasValue":false},"attackInnerRad":{"value":0,"hasValue":false},"attackOuterRad":{"value":0,"hasValue":false},"price":{"value":0,"hasValue":false},"loadCapacity":{"value":0,"hasValue":false},"bounty":{"value":0,"hasValue":false},"isNeutralOnly":{"value":false,"hasValue":false},"canBeDetected":{"value":false,"hasValue":false},"canCapture":{"value":false,"hasValue":false},"canMoveAfterBuild":{"value":false,"hasValue":false},"canAttackAfterMove":{"value":false,"hasValue":false},"canCounterAttack":{"value":false,"hasValue":false}},"price":"3"},{"rowNumber":1,"itemID":4,"itemName":"item","icon":"2","unitProperties":{"vision":{"value":0,"hasValue":false},"movement":{"value":0,"hasValue":false},"movementType":{"value":0,"hasValue":false},"baseDefence":{"value":0,"hasValue":false},"armorType":{"value":0,"hasValue":false},"lAttack":{"value":0,"hasValue":false},"mAttack":{"value":0,"hasValue":false},"hAttack":{"value":0,"hasValue":false},"uAttack":{"value":0,"hasValue":false},"ammo":{"value":0,"hasValue":false},"attackInnerRad":{"value":0,"hasValue":false},"attackOuterRad":{"value":0,"hasValue":false},"price":{"value":0,"hasValue":false},"loadCapacity":{"value":0,"hasValue":false},"bounty":{"value":0,"hasValue":false},"isNeutralOnly":{"value":false,"hasValue":false},"canBeDetected":{"value":false,"hasValue":false},"canCapture":{"value":false,"hasValue":false},"canMoveAfterBuild":{"value":false,"hasValue":false},"canAttackAfterMove":{"value":false,"hasValue":false},"canCounterAttack":{"value":false,"hasValue":false}},"price":"2"},{"rowNumber":2,"itemID":5,"itemName":"item","icon":0,"unitProperties":{"vision":{"value":0,"hasValue":false},"movement":{"value":0,"hasValue":false},"movementType":{"value":0,"hasValue":false},"baseDefence":{"value":0,"hasValue":false},"armorType":{"value":0,"hasValue":false},"lAttack":{"value":0,"hasValue":false},"mAttack":{"value":0,"hasValue":false},"hAttack":{"value":0,"hasValue":false},"uAttack":{"value":0,"hasValue":false},"ammo":{"value":0,"hasValue":false},"attackInnerRad":{"value":0,"hasValue":false},"attackOuterRad":{"value":0,"hasValue":false},"price":{"value":0,"hasValue":false},"loadCapacity":{"value":0,"hasValue":false},"bounty":{"value":0,"hasValue":false},"isNeutralOnly":{"value":false,"hasValue":false},"canBeDetected":{"value":false,"hasValue":false},"canCapture":{"value":false,"hasValue":false},"canMoveAfterBuild":{"value":false,"hasValue":false},"canAttackAfterMove":{"value":false,"hasValue":false},"canCounterAttack":{"value":false,"hasValue":false}},"price":"3"},{"rowNumber":2,"itemID":6,"itemName":"item","icon":"2","unitProperties":{"vision":{"value":0,"hasValue":false},"movement":{"value":0,"hasValue":false},"movementType":{"value":0,"hasValue":false},"baseDefence":{"value":0,"hasValue":false},"armorType":{"value":0,"hasValue":false},"lAttack":{"value":0,"hasValue":false},"mAttack":{"value":0,"hasValue":false},"hAttack":{"value":0,"hasValue":false},"uAttack":{"value":0,"hasValue":false},"ammo":{"value":0,"hasValue":false},"attackInnerRad":{"value":0,"hasValue":false},"attackOuterRad":{"value":0,"hasValue":false},"price":{"value":0,"hasValue":false},"loadCapacity":{"value":0,"hasValue":false},"bounty":{"value":0,"hasValue":false},"isNeutralOnly":{"value":false,"hasValue":false},"canBeDetected":{"value":false,"hasValue":false},"canCapture":{"value":false,"hasValue":false},"canMoveAfterBuild":{"value":false,"hasValue":false},"canAttackAfterMove":{"value":false,"hasValue":false},"canCounterAttack":{"value":false,"hasValue":false}},"price":"1"},{"rowNumber":3,"itemID":7,"itemName":"item","icon":0,"unitProperties":{"vision":{"value":0,"hasValue":false},"movement":{"value":0,"hasValue":false},"movementType":{"value":0,"hasValue":false},"baseDefence":{"value":0,"hasValue":false},"armorType":{"value":0,"hasValue":false},"lAttack":{"value":0,"hasValue":false},"mAttack":{"value":0,"hasValue":false},"hAttack":{"value":0,"hasValue":false},"uAttack":{"value":0,"hasValue":false},"ammo":{"value":0,"hasValue":false},"attackInnerRad":{"value":0,"hasValue":false},"attackOuterRad":{"value":0,"hasValue":false},"price":{"value":0,"hasValue":false},"loadCapacity":{"value":0,"hasValue":false},"bounty":{"value":0,"hasValue":false},"isNeutralOnly":{"value":false,"hasValue":false},"canBeDetected":{"value":false,"hasValue":false},"canCapture":{"value":false,"hasValue":false},"canMoveAfterBuild":{"value":false,"hasValue":false},"canAttackAfterMove":{"value":false,"hasValue":false},"canCounterAttack":{"value":false,"hasValue":false}},"price":"3"},{"rowNumber":3,"itemID":8,"itemName":"item","icon":"2","unitProperties":{"vision":{"value":0,"hasValue":false},"movement":{"value":0,"hasValue":false},"movementType":{"value":0,"hasValue":false},"baseDefence":{"value":0,"hasValue":false},"armorType":{"value":0,"hasValue":false},"lAttack":{"value":0,"hasValue":false},"mAttack":{"value":0,"hasValue":false},"hAttack":{"value":0,"hasValue":false},"uAttack":{"value":0,"hasValue":false},"ammo":{"value":0,"hasValue":false},"attackInnerRad":{"value":0,"hasValue":false},"attackOuterRad":{"value":0,"hasValue":false},"price":{"value":0,"hasValue":false},"loadCapacity":{"value":0,"hasValue":false},"bounty":{"value":0,"hasValue":false},"isNeutralOnly":{"value":false,"hasValue":false},"canBeDetected":{"value":false,"hasValue":false},"canCapture":{"value":false,"hasValue":false},"canMoveAfterBuild":{"value":false,"hasValue":false},"canAttackAfterMove":{"value":false,"hasValue":false},"canCounterAttack":{"value":false,"hasValue":false}},"price":"2"},{"rowNumber":3,"itemID":9,"itemName":"item","icon":0,"unitProperties":{"vision":{"value":0,"hasValue":false},"movement":{"value":0,"hasValue":false},"movementType":{"value":0,"hasValue":false},"baseDefence":{"value":0,"hasValue":false},"armorType":{"value":0,"hasValue":false},"lAttack":{"value":0,"hasValue":false},"mAttack":{"value":0,"hasValue":false},"hAttack":{"value":0,"hasValue":false},"uAttack":{"value":0,"hasValue":false},"ammo":{"value":0,"hasValue":false},"attackInnerRad":{"value":0,"hasValue":false},"attackOuterRad":{"value":0,"hasValue":false},"price":{"value":0,"hasValue":false},"loadCapacity":{"value":0,"hasValue":false},"bounty":{"value":0,"hasValue":false},"isNeutralOnly":{"value":false,"hasValue":false},"canBeDetected":{"value":false,"hasValue":false},"canCapture":{"value":false,"hasValue":false},"canMoveAfterBuild":{"value":false,"hasValue":false},"canAttackAfterMove":{"value":false,"hasValue":false},"canCounterAttack":{"value":false,"hasValue":false}},"price":"3"}]},{"fractionName":"League","unitName":"Machine Gunner","upgradeList":[]},{"fractionName":"League","unitName":"Tank","upgradeList":[]},{"fractionName":"League","unitName":"Transport","upgradeList":[]},{"fractionName":"League","unitName":"Bomber","upgradeList":[]},{"fractionName":"Reich","unitName":"Armored car","upgradeList":[]},{"fractionName":"Reich","unitName":"Artillery","upgradeList":[]},{"fractionName":"Reich","unitName":"Bazooka","upgradeList":[]},{"fractionName":"Reich","unitName":"Cavalry","upgradeList":[]},{"fractionName":"Reich","unitName":"Grenade Thrower","upgradeList":[]},{"fractionName":"Reich","unitName":"Infantry","upgradeList":[]},{"fractionName":"Reich","unitName":"Machine Gunner","upgradeList":[]},{"fractionName":"Reich","unitName":"Tank","upgradeList":[]},{"fractionName":"Reich","unitName":"Transport","upgradeList":[]},{"fractionName":"Reich","unitName":"Bomber","upgradeList":[]},{"fractionName":"Union","unitName":"Armored car","upgradeList":[]},{"fractionName":"Union","unitName":"Artillery","upgradeList":[]},{"fractionName":"Union","unitName":"Bazooka","upgradeList":[]},{"fractionName":"Union","unitName":"Cavalry","upgradeList":[]},{"fractionName":"Union","unitName":"Grenade Thrower","upgradeList":[]},{"fractionName":"Union","unitName":"Infantry","upgradeList":[]},{"fractionName":"Union","unitName":"Machine Gunner","upgradeList":[]},{"fractionName":"Union","unitName":"Tank","upgradeList":[]},{"fractionName":"Union","unitName":"Transport","upgradeList":[]},{"fractionName":"Union","unitName":"Bomber","upgradeList":[]}]}